whisper_turbo.py
whisper_turbo_mlx-0.0.1.dist-info/METADATA
whisper_turbo_mlx-0.0.1.dist-info/WHEEL
whisper_turbo_mlx-0.0.1.dist-info/entry_points.txt
whisper_turbo_mlx-0.0.1.dist-info/top_level.txt
whisper_turbo_mlx-0.0.1.dist-info/RECORD
