Metadata-Version: 2.1
Name: whisper-turbo-mlx
Version: 0.0.1
Summary: Whisper Turbo in MLX
Home-page: https://github.com/JosefAlbers/whisper-turbo-mlx
Author: Josef Albers
Author-email: albersj66@gmail.com
License: Apache License 2.0
Requires-Python: >=3.12.3
Requires-Dist: mlx ==0.18.1
Requires-Dist: numpy ==2.0.2
Requires-Dist: tiktoken ==0.8.0
Requires-Dist: huggingface-hub ==0.24.7
Requires-Dist: fire ==0.6.0
Requires-Dist: librosa ==0.10.2.post1
